.coveragerc
.editorconfig
.gitignore
.gitlab-ci.yml
.pre-commit-config.yaml
.zenodo.json
AUTHORS.rst
CITATION
CONTRIBUTING.rst
HISTORY.rst
LICENSE
MANIFEST.in
Makefile
README.rst
pyproject.toml
pytest.ini
tox.ini
.github/ISSUE_TEMPLATE.md
.github/create_release_from_gitlab_ci.sh
.gitlab/.gitkeep
.gitlab/merge_request_templates/merge_temp.md
data/World_UTM_Grid.zip
data/default_config.json
data/sentinel_2_index_shapefile_attr.zip
docs/Makefile
docs/authors.rst
docs/conf.py
docs/contributing.rst
docs/history.rst
docs/index.html
docs/index.rst
docs/installation.rst
docs/make.bat
docs/readme.rst
docs/usage.rst
docs/_static/custom.css
docs/images/fernlab_logo.png
docs/images/fernlab_logo.svg
docs/images/s2downloader_logo.jpg
docs/images/s2downloader_logo.png
docs/images/s2downloader_logo.svg
s2downloader/__init__.py
s2downloader/config.py
s2downloader/s2downloader.py
s2downloader/s2downloader_cli.py
s2downloader/utils.py
s2downloader/version.py
s2downloader.egg-info/PKG-INFO
s2downloader.egg-info/SOURCES.txt
s2downloader.egg-info/dependency_links.txt
s2downloader.egg-info/entry_points.txt
s2downloader.egg-info/not-zip-safe
s2downloader.egg-info/requires.txt
s2downloader.egg-info/top_level.txt