Metadata-Version: 2.1
Name: s2downloader
Version: 1.4.0
Summary: Downloader for Sentinel-2 from aws.
Author-email: FernLab <fernlab@gfz-potsdam.de>
License: EUPL-1.2
Project-URL: Source code, https://git.gfz-potsdam.de/fernlab/products/data-portal/s2downloader
Project-URL: Issue Tracker, https://git.gfz-potsdam.de/fernlab/products/data-portal/s2downloader/-/issues
Project-URL: Documentation, https://fernlab.git-pages.gfz-potsdam.de/products/data-portal/s2downloader/doc/
Project-URL: Change log, https://git.gfz-potsdam.de/fernlab/products/data-portal/s2downloader/-/blob/main/HISTORY.rst
Project-URL: Zenodo, https://zenodo.org/record/13123061
Keywords: s2downloader,remote sensing,sentinel-2,copernicus,multispectral,satellite imagery,geospatial,mosaic
Classifier: Development Status :: 5 - Production/Stable
Classifier: Intended Audience :: Science/Research
Classifier: Topic :: Scientific/Engineering
Classifier: License :: OSI Approved :: European Union Public Licence 1.2 (EUPL 1.2)
Classifier: Natural Language :: English
Classifier: Programming Language :: Python :: 3.10
Classifier: Programming Language :: Python :: 3.11
Classifier: Programming Language :: Python :: 3.12
Requires-Python: >=3.10
License-File: LICENSE
Requires-Dist: numpy>=2.0
Requires-Dist: affine
Requires-Dist: pyproj
Requires-Dist: geojson
Requires-Dist: geojson-pydantic
Requires-Dist: rasterio
Requires-Dist: geopandas>=1.0
Requires-Dist: shapely
Requires-Dist: pystac
Requires-Dist: geopy
Requires-Dist: pystac-client
Requires-Dist: pydantic
Provides-Extra: doc
Requires-Dist: sphinx>=4.1.1; extra == "doc"
Requires-Dist: sphinx-argparse; extra == "doc"
Requires-Dist: sphinx_rtd_theme; extra == "doc"
Requires-Dist: sphinx-autodoc-typehints; extra == "doc"
Requires-Dist: numpydoc>=1.7; extra == "doc"
Provides-Extra: test
Requires-Dist: pytest>=3; extra == "test"
Requires-Dist: pytest-cov; extra == "test"
Requires-Dist: pytest-reporter-html1; extra == "test"
Requires-Dist: urlchecker; extra == "test"
Provides-Extra: lint
Requires-Dist: pre-commit; extra == "lint"
Provides-Extra: dev
Requires-Dist: s2downloader[test]; extra == "dev"
Requires-Dist: s2downloader[doc]; extra == "dev"
Requires-Dist: s2downloader[lint]; extra == "dev"
Requires-Dist: twine; extra == "dev"
